megabots/__init__.py
megabots/bot.py
megabots/memory.py
megabots/prompt.py
megabots/utils.py
megabots/vectorstore.py
tests/__init__.py
tests/test_api.py
tests/test_bots.py
tests/test_memory.py
tests/test_ui.py
megabots-0.0.11.dist-info/LICENCE
megabots-0.0.11.dist-info/METADATA
megabots-0.0.11.dist-info/WHEEL
megabots-0.0.11.dist-info/top_level.txt
megabots-0.0.11.dist-info/RECORD
