Metadata-Version: 2.1
Name: megabots
Version: 0.0.11
Summary: 🤖 Megabots provides State-of-the-art, production ready bots made mega-easy, so you don't have to build them from scratch 🤯 Create a bot, now 🫵
Home-page: https://github.com/momegas/megabots
Author: Megaklis Vasilakis
Author-email: megaklis.vasilakis@gmail.com
License: MIT
Classifier: Development Status :: 4 - Beta
License-File: LICENCE
Requires-Dist: langchain
Requires-Dist: tiktoken
Requires-Dist: unstructured
Requires-Dist: fastapi
Requires-Dist: faiss-cpu
Requires-Dist: pdfminer.six
